geniushubclientalt/__init__.py
geniushubclientalt/_version.py
geniushubclientalt/const.py
geniushubclientalt/device.py
geniushubclientalt/issue.py
geniushubclientalt/session.py
geniushubclientalt/zone.py
geniushubclientalt-0.8.2.dist-info/licenses/LICENSE
geniushubclientalt-0.8.2.dist-info/METADATA
geniushubclientalt-0.8.2.dist-info/WHEEL
geniushubclientalt-0.8.2.dist-info/top_level.txt
geniushubclientalt-0.8.2.dist-info/RECORD
