Metadata-Version: 2.4
Name: geniushubclientalt
Version: 0.8.2
Summary: Library for Genius Hub
Author-email: Roger Selwyn <roger.selwyn@users.noreply.github.com>
Maintainer-email: Roger Selwyn <roger.selwyn@users.noreply.github.com>
License: MIT License
Project-URL: Documentation, https://rogerselwyn.github.io/geniushub-client-alt/
Project-URL: Repository, https://github.com/RogerSelwyn/geniushub-client-alt
Project-URL: Issues, https://github.com/RogerSelwyn/geniushub-client-alt/issues
Project-URL: Changelog, https://github.com/RogerSelwyn/geniushub-client-alt/blob/main/CHANGELOG.md
Keywords: Genius Hub,Heating
Platform: any
Classifier: Development Status :: 5 - Production/Stable
Classifier: Intended Audience :: Developers
Classifier: Topic :: Home Automation
Classifier: Topic :: Software Development :: Libraries
Classifier: Programming Language :: Python
Classifier: Programming Language :: Python :: 3.11
Classifier: Programming Language :: Python :: 3.12
Classifier: Programming Language :: Python :: 3.13
Classifier: Operating System :: OS Independent
Requires-Python: >=3.11
License-File: LICENSE
Requires-Dist: aiohttp>=3.8.5
Dynamic: license-file
